readable_password/__init__.py
readable_password/readable_password.py
readable_password/test_readable_password.py
readable_password-1.1.dist-info/LICENSE
readable_password-1.1.dist-info/METADATA
readable_password-1.1.dist-info/WHEEL
readable_password-1.1.dist-info/top_level.txt
readable_password-1.1.dist-info/RECORD
